[{"id": "tomate", "label": "tomate", "size": 2883}, {"id": "n", "label": "n", "size": 469}, {"id": "légumes", "label": "légumes", "size": 4812}, {"id": "épices", "label": "épices", "size": 461}, {"id": "pad", "label": "pad", "size": 123}, {"id": "thaï", "label": "thaï", "size": 472}, {"id": "saucisse", "label": "saucisse", "size": 258}, {"id": "veau", "label": "veau", "size": 297}, {"id": "suisse", "label": "suisse", "size": 4792}, {"id": "sauce", "label": "sauce", "size": 3553}, {"id": "gratin", "label": "gratin", "size": 539}, {"id": "crème", "label": "crème", "size": 1436}, {"id": "gorgonzola", "label": "gorgonzola", "size": 253}, {"id": "champignons", "label": "champignons", "size": 958}, {"id": "mozzarella", "label": "mozzarella", "size": 2909}, {"id": "tomates", "label": "tomates", "size": 1719}, {"id": "séchées", "label": "séchées", "size": 166}, {"id": "semoule", "label": "semoule", "size": 124}, {"id": "blé", "label": "blé", "size": 335}, {"id": "salade", "label": "salade", "size": 5030}, {"id": "galette", "label": "galette", "size": 278}, {"id": "polenta", "label": "polenta", "size": 187}, {"id": "gruyère", "label": "gruyère", "size": 941}, {"id": "lardons", "label": "lardons", "size": 188}, {"id": "saison", "label": "saison", "size": 275}, {"id": "porc", "label": "porc", "size": 1041}, {"id": "confites", "label": "confites", "size": 135}, {"id": "moutarde", "label": "moutarde", "size": 299}, {"id": "quinoa", "label": "quinoa", "size": 216}, {"id": "riz", "label": "riz", "size": 1384}, {"id": "quorn", "label": "quorn", "size": 408}, {"id": "soja", "label": "soja", "size": 404}, {"id": "gingembre", "label": "gingembre", "size": 106}, {"id": "confit", "label": "confit", "size": 184}, {"id": "penne", "label": "penne", "size": 907}, {"id": "lail", "label": "lail", "size": 556}, {"id": "pesto", "label": "pesto", "size": 1148}, {"id": "pousses", "label": "pousses", "size": 490}, {"id": "dépinards", "label": "dépinards", "size": 331}, {"id": "bowl", "label": "bowl", "size": 501}, {"id": "saumon", "label": "saumon", "size": 695}, {"id": "fumé", "label": "fumé", "size": 175}, {"id": "vinaigrette", "label": "vinaigrette", "size": 213}, {"id": "crevettes", "label": "crevettes", "size": 228}, {"id": "curry", "label": "curry", "size": 971}, {"id": "rouge", "label": "rouge", "size": 730}, {"id": "basmati", "label": "basmati", "size": 247}, {"id": "bio", "label": "bio", "size": 319}, {"id": "fusilli", "label": "fusilli", "size": 155}, {"id": "roquette", "label": "roquette", "size": 699}, {"id": "steak", "label": "steak", "size": 227}, {"id": "haché", "label": "haché", "size": 292}, {"id": "bœuf", "label": "bœuf", "size": 1015}, {"id": "jour", "label": "jour", "size": 459}, {"id": "ravioli", "label": "ravioli", "size": 142}, {"id": "chili", "label": "chili", "size": 188}, {"id": "nriz", "label": "nriz", "size": 129}, {"id": "sauté", "label": "sauté", "size": 384}, {"id": "poulet", "label": "poulet", "size": 1741}, {"id": "barbecue", "label": "barbecue", "size": 173}, {"id": "pommes", "label": "pommes", "size": 1556}, {"id": "vapeur", "label": "vapeur", "size": 120}, {"id": "lentilles", "label": "lentilles", "size": 360}, {"id": "nouilles", "label": "nouilles", "size": 461}, {"id": "bolognaise", "label": "bolognaise", "size": 231}, {"id": "dinde", "label": "dinde", "size": 732}, {"id": "piment", "label": "piment", "size": 176}, {"id": "basilic", "label": "basilic", "size": 1618}, {"id": "poivre", "label": "poivre", "size": 118}, {"id": "légumesprovenance", "label": "légumesprovenance", "size": 203}, {"id": "poireaux", "label": "poireaux", "size": 161}, {"id": "végétarien", "label": "végétarien", "size": 10116}, {"id": "pizza", "label": "pizza", "size": 2269}, {"id": "four", "label": "four", "size": 128}, {"id": "spaghetti", "label": "spaghetti", "size": 198}, {"id": "pâtes", "label": "pâtes", "size": 559}, {"id": "sautées", "label": "sautées", "size": 289}, {"id": "noix", "label": "noix", "size": 679}, {"id": "frits", "label": "frits", "size": 203}, {"id": "moment", "label": "moment", "size": 323}, {"id": "rôti", "label": "rôti", "size": 442}, {"id": "betterave", "label": "betterave", "size": 174}, {"id": "haricots", "label": "haricots", "size": 379}, {"id": "rouges", "label": "rouges", "size": 532}, {"id": "cheddar", "label": "cheddar", "size": 458}, {"id": "cordon", "label": "cordon", "size": 154}, {"id": "bleu", "label": "bleu", "size": 165}, {"id": "terre", "label": "terre", "size": 1673}, {"id": "carotte", "label": "carotte", "size": 247}, {"id": "brochette", "label": "brochette", "size": 144}, {"id": "volaille", "label": "volaille", "size": 180}, {"id": "sautés", "label": "sautés", "size": 126}, {"id": "choix", "label": "choix", "size": 160}, {"id": "jambon", "label": "jambon", "size": 1261}, {"id": "fromage", "label": "fromage", "size": 1187}, {"id": "chèvre", "label": "chèvre", "size": 1005}, {"id": "œuf", "label": "œuf", "size": 526}, {"id": "parfait", "label": "parfait", "size": 165}, {"id": "risotto", "label": "risotto", "size": 812}, {"id": "ecosse", "label": "ecosse", "size": 105}, {"id": "parmesan", "label": "parmesan", "size": 1049}, {"id": "complet", "label": "complet", "size": 140}, {"id": "courge", "label": "courge", "size": 470}, {"id": "grana", "label": "grana", "size": 933}, {"id": "padano", "label": "padano", "size": 770}, {"id": "pâte", "label": "pâte", "size": 115}, {"id": "râpé", "label": "râpé", "size": 109}, {"id": "margherita", "label": "margherita", "size": 106}, {"id": "grillé", "label": "grillé", "size": 302}, {"id": "rôtie", "label": "rôtie", "size": 204}, {"id": "falafel", "label": "falafel", "size": 1101}, {"id": "frais", "label": "frais", "size": 1363}, {"id": "choux", "label": "choux", "size": 357}, {"id": "croutons", "label": "croutons", "size": 351}, {"id": "herbes", "label": "herbes", "size": 474}, {"id": "provenance", "label": "provenance", "size": 1270}, {"id": "ch", "label": "ch", "size": 4660}, {"id": "gamme", "label": "gamme", "size": 1190}, {"id": "sandwichsnassortiment", "label": "sandwichsnassortiment", "size": 565}, {"id": "varié", "label": "varié", "size": 1087}, {"id": "fumée", "label": "fumée", "size": 589}, {"id": "mozza", "label": "mozza", "size": 244}, {"id": "escalope", "label": "escalope", "size": 132}, {"id": "emincé", "label": "emincé", "size": 684}, {"id": "maison", "label": "maison", "size": 889}, {"id": "carottes", "label": "carottes", "size": 1098}, {"id": "kebab", "label": "kebab", "size": 134}, {"id": "planted", "label": "planted", "size": 261}, {"id": "aubergines", "label": "aubergines", "size": 484}, {"id": "grillées", "label": "grillées", "size": 422}, {"id": "pain", "label": "pain", "size": 1318}, {"id": "quiche", "label": "quiche", "size": 341}, {"id": "omelette", "label": "omelette", "size": 100}, {"id": "verte", "label": "verte", "size": 819}, {"id": "tofu", "label": "tofu", "size": 669}, {"id": "lait", "label": "lait", "size": 427}, {"id": "coco", "label": "coco", "size": 325}, {"id": "croquants", "label": "croquants", "size": 366}, {"id": "brocolis", "label": "brocolis", "size": 234}, {"id": "chou", "label": "chou", "size": 324}, {"id": "burger", "label": "burger", "size": 1051}, {"id": "végan", "label": "végan", "size": 233}, {"id": "frites", "label": "frites", "size": 836}, {"id": "végétarienne", "label": "végétarienne", "size": 199}, {"id": "épinards", "label": "épinards", "size": 618}, {"id": "dahl", "label": "dahl", "size": 160}, {"id": "blanc", "label": "blanc", "size": 363}, {"id": "coriandre", "label": "coriandre", "size": 739}, {"id": "gnocchi", "label": "gnocchi", "size": 524}, {"id": "petits", "label": "petits", "size": 576}, {"id": "pois", "label": "pois", "size": 911}, {"id": "al", "label": "al", "size": 227}, {"id": "fraiche", "label": "fraiche", "size": 359}, {"id": "aubergine", "label": "aubergine", "size": 161}, {"id": "confite", "label": "confite", "size": 104}, {"id": "grillés", "label": "grillés", "size": 528}, {"id": "façon", "label": "façon", "size": 146}, {"id": "grillade", "label": "grillade", "size": 455}, {"id": "végétariennensteak", "label": "végétariennensteak", "size": 172}, {"id": "carte", "label": "carte", "size": 275}, {"id": "pizzasnassortiment", "label": "pizzasnassortiment", "size": 222}, {"id": "saisons", "label": "saisons", "size": 284}, {"id": "reine", "label": "reine", "size": 350}, {"id": "buffalina", "label": "buffalina", "size": 132}, {"id": "pièce", "label": "pièce", "size": 217}, {"id": "brunoise", "label": "brunoise", "size": 181}, {"id": "copeaux", "label": "copeaux", "size": 413}, {"id": "dagneau", "label": "dagneau", "size": 100}, {"id": "verteprovenance", "label": "verteprovenance", "size": 376}, {"id": "crudités", "label": "crudités", "size": 1398}, {"id": "crémeux", "label": "crémeux", "size": 101}, {"id": "champignon", "label": "champignon", "size": 310}, {"id": "vegan", "label": "vegan", "size": 379}, {"id": "paprika", "label": "paprika", "size": 158}, {"id": "farfalle", "label": "farfalle", "size": 166}, {"id": "pomme", "label": "pomme", "size": 792}, {"id": "boeuf", "label": "boeuf", "size": 1029}, {"id": "entrecôte", "label": "entrecôte", "size": 182}, {"id": "béarnaise", "label": "béarnaise", "size": 148}, {"id": "ravioles", "label": "ravioles", "size": 131}, {"id": "rougentagliata", "label": "rougentagliata", "size": 153}, {"id": "frite", "label": "frite", "size": 154}, {"id": "saladeprovenance", "label": "saladeprovenance", "size": 686}, {"id": "sésame", "label": "sésame", "size": 203}, {"id": "concombre", "label": "concombre", "size": 575}, {"id": "noir", "label": "noir", "size": 106}, {"id": "maïs", "label": "maïs", "size": 560}, {"id": "filet", "label": "filet", "size": 304}, {"id": "boulettes", "label": "boulettes", "size": 144}, {"id": "raclette", "label": "raclette", "size": 385}, {"id": "napolitaine", "label": "napolitaine", "size": 149}, {"id": "lasagne", "label": "lasagne", "size": 162}, {"id": "lancienne", "label": "lancienne", "size": 223}, {"id": "mariné", "label": "mariné", "size": 319}, {"id": "boulgour", "label": "boulgour", "size": 141}, {"id": "amandes", "label": "amandes", "size": 396}, {"id": "julienne", "label": "julienne", "size": 191}, {"id": "vin", "label": "vin", "size": 416}, {"id": "pousse", "label": "pousse", "size": 142}, {"id": "beurre", "label": "beurre", "size": 652}, {"id": "verts", "label": "verts", "size": 141}, {"id": "thym", "label": "thym", "size": 284}, {"id": "fleur", "label": "fleur", "size": 212}, {"id": "sandwich", "label": "sandwich", "size": 613}, {"id": "composés", "label": "composés", "size": 162}, {"id": "dun", "label": "dun", "size": 162}, {"id": "mélange", "label": "mélange", "size": 210}, {"id": "fèves", "label": "fèves", "size": 144}, {"id": "chiches", "label": "chiches", "size": 257}, {"id": "cornichons", "label": "cornichons", "size": 317}, {"id": "tarator", "label": "tarator", "size": 105}, {"id": "chiche", "label": "chiche", "size": 199}, {"id": "taouk", "label": "taouk", "size": 131}, {"id": "npoulet", "label": "npoulet", "size": 143}, {"id": "citron", "label": "citron", "size": 452}, {"id": "sept", "label": "sept", "size": 130}, {"id": "libanaises", "label": "libanaises", "size": 130}, {"id": "chawarma", "label": "chawarma", "size": 137}, {"id": "broche", "label": "broche", "size": 152}, {"id": "avec", "label": "avec", "size": 1142}, {"id": "persil", "label": "persil", "size": 290}, {"id": "épinard", "label": "épinard", "size": 104}, {"id": "patate", "label": "patate", "size": 206}, {"id": "douce", "label": "douce", "size": 283}, {"id": "miel", "label": "miel", "size": 641}, {"id": "vert", "label": "vert", "size": 353}, {"id": "soba", "label": "soba", "size": 112}, {"id": "taboulé", "label": "taboulé", "size": 133}, {"id": "graines", "label": "graines", "size": 289}, {"id": "pané", "label": "pané", "size": 142}, {"id": "des", "label": "des", "size": 328}, {"id": "cuisse", "label": "cuisse", "size": 145}, {"id": "fruit", "label": "fruit", "size": 133}, {"id": "nlégumes", "label": "nlégumes", "size": 101}, {"id": "fromages", "label": "fromages", "size": 205}, {"id": "italian", "label": "italian", "size": 138}, {"id": "rosso", "label": "rosso", "size": 133}, {"id": "ricotta", "label": "ricotta", "size": 535}, {"id": "oeuf", "label": "oeuf", "size": 412}, {"id": "salami", "label": "salami", "size": 202}, {"id": "big", "label": "big", "size": 230}, {"id": "burgernbun", "label": "burgernbun", "size": 103}, {"id": "oignons", "label": "oignons", "size": 1043}, {"id": "confits", "label": "confits", "size": 318}, {"id": "pasta", "label": "pasta", "size": 666}, {"id": "chefnpenne", "label": "chefnpenne", "size": 107}, {"id": "cocotte", "label": "cocotte", "size": 298}, {"id": "balsamique", "label": "balsamique", "size": 167}, {"id": "émincé", "label": "émincé", "size": 124}, {"id": "parfumé", "label": "parfumé", "size": 335}, {"id": "printemps", "label": "printemps", "size": 146}, {"id": "cannelloni", "label": "cannelloni", "size": 105}, {"id": "gratiné", "label": "gratiné", "size": 139}, {"id": "poivrons", "label": "poivrons", "size": 740}, {"id": "crémeuse", "label": "crémeuse", "size": 173}, {"id": "rôties", "label": "rôties", "size": 266}, {"id": "gyoza", "label": "gyoza", "size": 138}, {"id": "wok", "label": "wok", "size": 109}, {"id": "focaccia", "label": "focaccia", "size": 579}, {"id": "nsalade", "label": "nsalade", "size": 166}, {"id": "tartare", "label": "tartare", "size": 300}, {"id": "chorizo", "label": "chorizo", "size": 101}, {"id": "échalotes", "label": "échalotes", "size": 110}, {"id": "oignon", "label": "oignon", "size": 147}, {"id": "alla", "label": "alla", "size": 312}, {"id": "italiennensalade", "label": "italiennensalade", "size": 273}, {"id": "olives", "label": "olives", "size": 993}, {"id": "césar", "label": "césar", "size": 175}, {"id": "bun", "label": "bun", "size": 410}, {"id": "jasmin", "label": "jasmin", "size": 162}, {"id": "yogourt", "label": "yogourt", "size": 454}, {"id": "country", "label": "country", "size": 327}, {"id": "cacahuètes", "label": "cacahuètes", "size": 131}, {"id": "croustillant", "label": "croustillant", "size": 152}, {"id": "pita", "label": "pita", "size": 452}, {"id": "purée", "label": "purée", "size": 183}, {"id": "raïta", "label": "raïta", "size": 137}, {"id": "feta", "label": "feta", "size": 222}, {"id": "tortellini", "label": "tortellini", "size": 180}, {"id": "couscous", "label": "couscous", "size": 106}, {"id": "raisins", "label": "raisins", "size": 260}, {"id": "grillée", "label": "grillée", "size": 171}, {"id": "nsauce", "label": "nsauce", "size": 193}, {"id": "braisé", "label": "braisé", "size": 190}, {"id": "di", "label": "di", "size": 256}, {"id": "fruits", "label": "fruits", "size": 636}, {"id": "falafelnsalade", "label": "falafelnsalade", "size": 358}, {"id": "végé", "label": "végé", "size": 131}, {"id": "sandwichs", "label": "sandwichs", "size": 512}, {"id": "végénassortiment", "label": "végénassortiment", "size": 165}, {"id": "veggienbuns", "label": "veggienbuns", "size": 111}, {"id": "petit", "label": "petit", "size": 177}, {"id": "servie", "label": "servie", "size": 187}, {"id": "jus", "label": "jus", "size": 250}, {"id": "dherbes", "label": "dherbes", "size": 137}, {"id": "cru", "label": "cru", "size": 411}, {"id": "chips", "label": "chips", "size": 679}, {"id": "and", "label": "and", "size": 382}, {"id": "séchée", "label": "séchée", "size": 362}, {"id": "tagliatelles", "label": "tagliatelles", "size": 128}, {"id": "fao", "label": "fao", "size": 132}, {"id": "chicken", "label": "chicken", "size": 296}, {"id": "céréales", "label": "céréales", "size": 283}, {"id": "batavia", "label": "batavia", "size": 102}, {"id": "menthe", "label": "menthe", "size": 110}, {"id": "veggie", "label": "veggie", "size": 571}, {"id": "courgettes", "label": "courgettes", "size": 398}, {"id": "parmentier", "label": "parmentier", "size": 112}, {"id": "lhuile", "label": "lhuile", "size": 171}, {"id": "nau", "label": "nau", "size": 108}, {"id": "frit", "label": "frit", "size": 196}, {"id": "rumsteak", "label": "rumsteak", "size": 114}, {"id": "houmous", "label": "houmous", "size": 112}, {"id": "protéine", "label": "protéine", "size": 100}, {"id": "noisette", "label": "noisette", "size": 138}, {"id": "thon", "label": "thon", "size": 515}, {"id": "duo", "label": "duo", "size": 113}, {"id": "supplément", "label": "supplément", "size": 108}, {"id": "panini", "label": "panini", "size": 181}, {"id": "caulys", "label": "caulys", "size": 106}, {"id": "potatoes", "label": "potatoes", "size": 357}, {"id": "verde", "label": "verde", "size": 218}, {"id": "escargot", "label": "escargot", "size": 203}, {"id": "sel", "label": "sel", "size": 146}, {"id": "viande", "label": "viande", "size": 496}, {"id": "servi", "label": "servi", "size": 576}, {"id": "mayonnaise", "label": "mayonnaise", "size": 275}, {"id": "oeufs", "label": "oeufs", "size": 166}, {"id": "croûtons", "label": "croûtons", "size": 248}, {"id": "mexican", "label": "mexican", "size": 195}, {"id": "msc", "label": "msc", "size": 297}, {"id": "jaunes", "label": "jaunes", "size": 106}, {"id": "coleslaw", "label": "coleslaw", "size": 165}, {"id": "grta", "label": "grta", "size": 198}, {"id": "buffet", "label": "buffet", "size": 840}, {"id": "baconprovenance", "label": "baconprovenance", "size": 112}, {"id": "ntomate", "label": "ntomate", "size": 133}, {"id": "radis", "label": "radis", "size": 110}, {"id": "asperges", "label": "asperges", "size": 175}, {"id": "fraîche", "label": "fraîche", "size": 189}, {"id": "olivesprovenance", "label": "olivesprovenance", "size": 139}, {"id": "sucrine", "label": "sucrine", "size": 439}, {"id": "tian", "label": "tian", "size": 289}, {"id": "dail", "label": "dail", "size": 109}, {"id": "salades", "label": "salades", "size": 157}, {"id": "bar", "label": "bar", "size": 120}, {"id": "ours", "label": "ours", "size": 176}, {"id": "italienne", "label": "italienne", "size": 272}, {"id": "boucher", "label": "boucher", "size": 107}, {"id": "rigate", "label": "rigate", "size": 172}, {"id": "ratatouille", "label": "ratatouille", "size": 119}, {"id": "e", "label": "e", "size": 129}, {"id": "asie", "label": "asie", "size": 259}, {"id": "cerises", "label": "cerises", "size": 139}, {"id": "edamame", "label": "edamame", "size": 108}, {"id": "corsé", "label": "corsé", "size": 146}, {"id": "pointe", "label": "pointe", "size": 127}, {"id": "mayo", "label": "mayo", "size": 222}, {"id": "buffala", "label": "buffala", "size": 178}, {"id": "chorizoprovenance", "label": "chorizoprovenance", "size": 125}, {"id": "cerise", "label": "cerise", "size": 109}, {"id": "chaud", "label": "chaud", "size": 138}, {"id": "momentnassortiment", "label": "momentnassortiment", "size": 177}, {"id": "kale", "label": "kale", "size": 109}, {"id": "mozzaprovenance", "label": "mozzaprovenance", "size": 509}, {"id": "buffalinaprovenance", "label": "buffalinaprovenance", "size": 143}, {"id": "accompagné", "label": "accompagné", "size": 297}, {"id": "grill", "label": "grill", "size": 287}, {"id": "huile", "label": "huile", "size": 160}, {"id": "champignonsnprovenance", "label": "champignonsnprovenance", "size": 220}, {"id": "fais", "label": "fais", "size": 177}, {"id": "ta", "label": "ta", "size": 179}, {"id": "twisted", "label": "twisted", "size": 306}, {"id": "mêléen", "label": "mêléen", "size": 123}, {"id": "swiss", "label": "swiss", "size": 179}, {"id": "gr", "label": "gr", "size": 201}, {"id": "mêléeprovenance", "label": "mêléeprovenance", "size": 443}, {"id": "grèce", "label": "grèce", "size": 115}, {"id": "blancprovenance", "label": "blancprovenance", "size": 132}, {"id": "bb", "label": "bb", "size": 104}, {"id": "options", "label": "options", "size": 180}, {"id": "végétariennesnchèvre", "label": "végétariennesnchèvre", "size": 180}, {"id": "humus", "label": "humus", "size": 218}, {"id": "inspiration", "label": "inspiration", "size": 250}, {"id": "viennoiseriesncroissants", "label": "viennoiseriesncroissants", "size": 200}, {"id": "croissants", "label": "croissants", "size": 199}, {"id": "chocolat", "label": "chocolat", "size": 401}, {"id": "sucre", "label": "sucre", "size": 239}, {"id": "brioche", "label": "brioche", "size": 241}, {"id": "pépites", "label": "pépites", "size": 200}, {"id": "cannelé", "label": "cannelé", "size": 160}, {"id": "vanille", "label": "vanille", "size": 163}, {"id": "caracs", "label": "caracs", "size": 160}, {"id": "cookies", "label": "cookies", "size": 160}, {"id": "rucolla", "label": "rucolla", "size": 184}, {"id": "froid", "label": "froid", "size": 312}, {"id": "chaudnsalade", "label": "chaudnsalade", "size": 219}, {"id": "légumineuses", "label": "légumineuses", "size": 241}, {"id": "nracines", "label": "nracines", "size": 220}, {"id": "vaud", "label": "vaud", "size": 120}, {"id": "roquettesprovenance", "label": "roquettesprovenance", "size": 106}, {"id": "qui", "label": "qui", "size": 109}, {"id": "romesco", "label": "romesco", "size": 124}, {"id": "rucollaprovenance", "label": "rucollaprovenance", "size": 319}, {"id": "burratina", "label": "burratina", "size": 133}, {"id": "saladesnfalafel", "label": "saladesnfalafel", "size": 209}, {"id": "pastrami", "label": "pastrami", "size": 209}, {"id": "cesarprovenance", "label": "cesarprovenance", "size": 209}, {"id": "verdurantomates", "label": "verdurantomates", "size": 166}, {"id": "margueritantomate", "label": "margueritantomate", "size": 157}, {"id": "mielntomate", "label": "mielntomate", "size": 157}, {"id": "buffalinantomates", "label": "buffalinantomates", "size": 149}, {"id": "norvégiennentomate", "label": "norvégiennentomate", "size": 119}, {"id": "mscnnorvège", "label": "mscnnorvège", "size": 115}, {"id": "chorizontomate", "label": "chorizontomate", "size": 116}, {"id": "orientalentomate", "label": "orientalentomate", "size": 131}, {"id": "merguezprovenance", "label": "merguezprovenance", "size": 131}, {"id": "margerita", "label": "margerita", "size": 103}, {"id": "sw", "label": "sw", "size": 248}, {"id": "assortiments", "label": "assortiments", "size": 198}, {"id": "poids", "label": "poids", "size": 163}, {"id": "dessert", "label": "dessert", "size": 295}, {"id": "cartenfait", "label": "cartenfait", "size": 308}, {"id": "menunsalade", "label": "menunsalade", "size": 113}, {"id": "glacée", "label": "glacée", "size": 106}]